fastapi_returns_router/__init__.py
fastapi_returns_router/_wrappers.py
fastapi_returns_router/returns_router.py
fastapi_returns_router-1.0.1.dist-info/WHEEL
fastapi_returns_router-1.0.1.dist-info/METADATA
fastapi_returns_router-1.0.1.dist-info/RECORD
